{
    "symbol_name": "container",
    "direction": "top2down",
    "children": [
        {
            "symbol_name": "container",
            "direction": "left2right",
            "children": [
                {
                    "symbol_name": "textbox",
                    "direction": "top2down",
                    "children": [
                        "text001"
                    ]
                },
                "image001"
            ]
        },
        {
            "symbol_name": "textbox",
            "direction": "top2down",
            "children": [
                {
                    "symbol_name": "container",
                    "direction": "left2right",
                    "children": [
                        {
                            "symbol_name": "textbox",
                            "direction": "top2down",
                            "children": [
                                "text002"
                            ]
                        },
                        "image002"
                    ]
                },
                "text003"
            ]
        },
        {
            "symbol_name": "layerlist_slider",
            "direction": "left2right",
            "children": [
                {
                    "symbol_name": "nac_title",
                    "direction": "top2down",
                    "children": []
                },
                {
                    "symbol_name": "nac_item",
                    "direction": "left2right",
                    "children": [
                        {
                            "symbol_name": "textbox",
                            "direction": "top2down",
                            "children": [
                                "text004"
                            ]
                        },
                        "image003"
                    ]
                },
                {
                    "symbol_name": "nac_title",
                    "direction": "top2down",
                    "children": []
                },
                {
                    "symbol_name": "nac_item",
                    "direction": "left2right",
                    "children": [
                        {
                            "symbol_name": "textbox",
                            "direction": "top2down",
                            "children": [
                                "text005"
                            ]
                        },
                        "image004"
                    ]
                },
                {
                    "symbol_name": "nac_title",
                    "direction": "top2down",
                    "children": []
                },
                {
                    "symbol_name": "nac_item",
                    "direction": "left2right",
                    "children": [
                        {
                            "symbol_name": "textbox",
                            "direction": "top2down",
                            "children": [
                                "text006"
                            ]
                        },
                        "image005"
                    ]
                },
                {
                    "symbol_name": "nac_title",
                    "direction": "top2down",
                    "children": []
                },
                {
                    "symbol_name": "nac_item",
                    "direction": "left2right",
                    "children": [
                        {
                            "symbol_name": "textbox",
                            "direction": "top2down",
                            "children": [
                                "text007"
                            ]
                        },
                        "image006"
                    ]
                },
                {
                    "symbol_name": "nac_title",
                    "direction": "top2down",
                    "children": []
                },
                {
                    "symbol_name": "nac_item",
                    "direction": "left2right",
                    "children": [
                        {
                            "symbol_name": "textbox",
                            "direction": "top2down",
                            "children": [
                                "text008"
                            ]
                        },
                        "image007"
                    ]
                }
            ]
        }
    ]
}